p65a/__init__.py
p65a/assembler.py
p65a/symbolics.py
p65a-0.0.1.dist-info/LICENSE
p65a-0.0.1.dist-info/WHEEL
p65a-0.0.1.dist-info/METADATA
p65a-0.0.1.dist-info/RECORD
