Metadata-Version: 2.1
Name: p65a
Version: 0.0.1
Summary: Pythonic 6502 Assembler: An experimental alternative to traditional assemblers.
Author-email: David Buchanan <d@vidbuchanan.co.uk>
Requires-Python: >=3.10
Classifier: Programming Language :: Python :: 3
Classifier: License :: OSI Approved :: MIT License
Classifier: Operating System :: OS Independent
Classifier: Development Status :: 3 - Alpha
Classifier: Intended Audience :: Developers
Classifier: Natural Language :: English
Classifier: Topic :: Software Development :: Assemblers
Classifier: Topic :: Software Development :: Code Generators
Project-URL: Bug Tracker, https://github.com/DavidBuchanan314/p65a/issues
Project-URL: Homepage, https://github.com/DavidBuchanan314/p65a
